{
  "SPDXID" : "SPDXRef-DOCUMENT",
  "spdxVersion" : "SPDX-2.3",
  "creationInfo" : {
    "comment" : "Converted from CycloneDX spec version 1.4",
    "created" : "2023-07-17T14:00:44Z",
    "creators" : [ "Tool: CycloneDX:cyclonedx-bom-3.11.2", "Tool: CycloneDX:cyclonedx-python-lib-3.1.1", "Tool: CycloneToSpdx-0.1.4" ],
    "licenseListVersion" : "3.21"
  },
  "name" : "From-Cyclone-DX",
  "dataLicense" : "CC0-1.0",
  "annotations" : [ {
    "annotationDate" : "2023-07-17T14:00:46Z",
    "annotationType" : "OTHER",
    "annotator" : "Tool: CycloneToSpdx",
    "comment" : "MISSING_CDX_PROPERTY:extensions={}"
  } ],
  "documentNamespace" : "https://cyclonedx/2b324b4a-a0b2-469e-b21d-e9f42c415fb5_1",
  "packages" : [ {
    "SPDXID" : "SPDXRef-eb6bbdb1-f6c3-4135-ab22-c47d900d6066",
    "annotations" : [ {
      "annotationDate" : "2023-07-17T14:00:46Z",
      "annotationType" : "OTHER",
      "annotator" : "Tool: CycloneToSpdx",
      "comment" : "MISSING_CDX_PROPERTY:componentType=\"LIBRARY\""
    } ],
    "copyrightText" : "NOASSERTION",
    "downloadLocation" : "NOASSERTION",
    "externalRefs" : [ {
      "referenceCategory" : "PACKAGE-MANAGER",
      "referenceLocator" : "pkg:pypi/typer@0.9.0",
      "referenceType" : "purl"
    } ],
    "filesAnalyzed" : false,
    "licenseConcluded" : "NOASSERTION",
    "licenseDeclared" : "NOASSERTION",
    "name" : "typer",
    "primaryPackagePurpose" : "LIBRARY",
    "versionInfo" : "0.9.0"
  }, {
    "SPDXID" : "SPDXRef-775bfc1d-ee89-4a62-88d5-c8b9d750a144",
    "annotations" : [ {
      "annotationDate" : "2023-07-17T14:00:46Z",
      "annotationType" : "OTHER",
      "annotator" : "Tool: CycloneToSpdx",
      "comment" : "MISSING_CDX_PROPERTY:componentType=\"LIBRARY\""
    } ],
    "copyrightText" : "NOASSERTION",
    "downloadLocation" : "NOASSERTION",
    "externalRefs" : [ {
      "referenceCategory" : "PACKAGE-MANAGER",
      "referenceLocator" : "pkg:pypi/jsonschema@4.18.2",
      "referenceType" : "purl"
    } ],
    "filesAnalyzed" : false,
    "licenseConcluded" : "NOASSERTION",
    "licenseDeclared" : "NOASSERTION",
    "name" : "jsonschema",
    "primaryPackagePurpose" : "LIBRARY",
    "versionInfo" : "4.18.2"
  }, {
    "SPDXID" : "SPDXRef-48f3a7fc-eea4-4fe3-805e-0322b612040b",
    "annotations" : [ {
      "annotationDate" : "2023-07-17T14:00:46Z",
      "annotationType" : "OTHER",
      "annotator" : "Tool: CycloneToSpdx",
      "comment" : "MISSING_CDX_PROPERTY:componentType=\"LIBRARY\""
    } ],
    "copyrightText" : "NOASSERTION",
    "downloadLocation" : "NOASSERTION",
    "externalRefs" : [ {
      "referenceCategory" : "PACKAGE-MANAGER",
      "referenceLocator" : "pkg:pypi/xmlschema@2.3.1",
      "referenceType" : "purl"
    } ],
    "filesAnalyzed" : false,
    "licenseConcluded" : "NOASSERTION",
    "licenseDeclared" : "NOASSERTION",
    "name" : "xmlschema",
    "primaryPackagePurpose" : "LIBRARY",
    "versionInfo" : "2.3.1"
  } ],
  "relationships" : [ {
    "spdxElementId" : "SPDXRef-DOCUMENT",
    "relationshipType" : "DESCRIBES",
    "relatedSpdxElement" : "SPDXRef-775bfc1d-ee89-4a62-88d5-c8b9d750a144"
  }, {
    "spdxElementId" : "SPDXRef-DOCUMENT",
    "relationshipType" : "DESCRIBES",
    "relatedSpdxElement" : "SPDXRef-48f3a7fc-eea4-4fe3-805e-0322b612040b"
  }, {
    "spdxElementId" : "SPDXRef-DOCUMENT",
    "relationshipType" : "DESCRIBES",
    "relatedSpdxElement" : "SPDXRef-eb6bbdb1-f6c3-4135-ab22-c47d900d6066"
  } ]
}